vanityurls/__init__.py
vanityurls/admin.py
vanityurls/apps.py
vanityurls/middleware.py
vanityurls/models.py
vanityurls/fixtures/basic-db.json
vanityurls/migrations/0001_initial.py
vanityurls/migrations/0002_alter_vanityurl_options_alter_vanityurl_vanity_url.py
vanityurls/migrations/0003_vanityurl_code_alter_vanityurl_vanity_url.py
vanityurls/migrations/0004_category_vanityurl_category.py
vanityurls/migrations/__init__.py
django_vanityurls-2.0.dist-info/METADATA
django_vanityurls-2.0.dist-info/WHEEL
django_vanityurls-2.0.dist-info/licenses/LICENSE
django_vanityurls-2.0.dist-info/RECORD
